tromero/__init__.py
tromero/cli.py
tromero/constants.py
tromero/fine_tuning.py
tromero/fine_tuning_models.py
tromero/fine_tuning_requests.py
tromero/tromero_requests.py
tromero/tromero_utils.py
tromero/wrapper.py
tromero_tailor/__init__.py
tromero_tailor/cli.py
tromero_tailor/constants.py
tromero_tailor/fine_tuning.py
tromero_tailor/fine_tuning_models.py
tromero_tailor/fine_tuning_requests.py
tromero_tailor/tromero_requests.py
tromero_tailor/tromero_utils.py
tromero_tailor/wrapper.py
tromero-0.0.12.dist-info/METADATA
tromero-0.0.12.dist-info/WHEEL
tromero-0.0.12.dist-info/entry_points.txt
tromero-0.0.12.dist-info/top_level.txt
tromero-0.0.12.dist-info/RECORD
