Metadata-Version: 2.1
Name: tromero
Version: 0.0.12
Summary: Python client for Tromero Cloud Platform!
Home-page: https://www.tromero.ai/
Author: Tromero
Author-email: admin@tromero.ai
License: MIT
Classifier: Programming Language :: Python :: 3
Classifier: License :: OSI Approved :: MIT License
Classifier: Operating System :: OS Independent
Requires-Python: >=3.6
Requires-Dist: annotated-types ==0.6.0
Requires-Dist: anyio ==4.3.0
Requires-Dist: certifi ==2024.7.4
Requires-Dist: charset-normalizer ==3.3.2
Requires-Dist: distro ==1.9.0
Requires-Dist: h11 ==0.14.0
Requires-Dist: httpcore ==1.0.5
Requires-Dist: httpx ==0.27.0
Requires-Dist: idna ==3.7
Requires-Dist: openai ==1.16.1
Requires-Dist: pydantic ==2.6.4
Requires-Dist: pydantic-core ==2.16.3
Requires-Dist: requests ==2.32.2
Requires-Dist: setuptools ==70.0.0
Requires-Dist: sniffio ==1.3.1
Requires-Dist: tqdm ==4.66.3
Requires-Dist: typing-extensions ==4.10.0
Requires-Dist: urllib3 ==2.2.2
Requires-Dist: fire
